odoo/addons/purchase_order_uninvoiced_amount/README.rst
odoo/addons/purchase_order_uninvoiced_amount/__init__.py
odoo/addons/purchase_order_uninvoiced_amount/__manifest__.py
odoo/addons/purchase_order_uninvoiced_amount/i18n/en_US.po
odoo/addons/purchase_order_uninvoiced_amount/i18n/es.po
odoo/addons/purchase_order_uninvoiced_amount/i18n/it.po
odoo/addons/purchase_order_uninvoiced_amount/i18n/pt_BR.po
odoo/addons/purchase_order_uninvoiced_amount/i18n/purchase_order_uninvoiced_amount.pot
odoo/addons/purchase_order_uninvoiced_amount/models/__init__.py
odoo/addons/purchase_order_uninvoiced_amount/models/purchase_order.py
odoo/addons/purchase_order_uninvoiced_amount/readme/CONTRIBUTORS.md
odoo/addons/purchase_order_uninvoiced_amount/readme/DESCRIPTION.md
odoo/addons/purchase_order_uninvoiced_amount/static/description/icon.png
odoo/addons/purchase_order_uninvoiced_amount/static/description/index.html
odoo/addons/purchase_order_uninvoiced_amount/tests/__init__.py
odoo/addons/purchase_order_uninvoiced_amount/tests/test_purchase_order_uninvoiced_amount.py
odoo/addons/purchase_order_uninvoiced_amount/views/purchase_order_view.xml
odoo_addon_purchase_order_uninvoiced_amount-18.0.1.0.0.3.dist-info/METADATA
odoo_addon_purchase_order_uninvoiced_amount-18.0.1.0.0.3.dist-info/WHEEL
odoo_addon_purchase_order_uninvoiced_amount-18.0.1.0.0.3.dist-info/top_level.txt
odoo_addon_purchase_order_uninvoiced_amount-18.0.1.0.0.3.dist-info/RECORD
